arr_suite_mcp/__init__.py
arr_suite_mcp/config.py
arr_suite_mcp/server.py
arr_suite_mcp-1.0.0.dist-info/licenses/LICENSE
arr_suite_mcp-1.0.0.dist-info/METADATA
arr_suite_mcp-1.0.0.dist-info/WHEEL
arr_suite_mcp-1.0.0.dist-info/entry_points.txt
arr_suite_mcp-1.0.0.dist-info/top_level.txt
arr_suite_mcp-1.0.0.dist-info/RECORD
