Metadata-Version: 2.4
Name: arr-suite-mcp
Version: 1.0.0
Summary: Intelligent MCP server for Plex and the complete *arr media automation suite (Sonarr, Radarr, Prowlarr, Bazarr, Overseerr)
Author: Arr Suite MCP Contributors
License: MIT
Project-URL: Homepage, https://github.com/shaktech786/arr-suite-mcp-server
Project-URL: Documentation, https://github.com/shaktech786/arr-suite-mcp-server#readme
Project-URL: Repository, https://github.com/shaktech786/arr-suite-mcp-server
Project-URL: Issues, https://github.com/shaktech786/arr-suite-mcp-server/issues
Keywords: mcp,sonarr,radarr,prowlarr,bazarr,overseerr,media,automation
Classifier: Development Status :: 4 - Beta
Classifier: Intended Audience :: Developers
Classifier: License :: OSI Approved :: MIT License
Classifier: Programming Language :: Python :: 3
Classifier: Programming Language :: Python :: 3.10
Classifier: Programming Language :: Python :: 3.11
Classifier: Programming Language :: Python :: 3.12
Requires-Python: >=3.10
License-File: LICENSE
Requires-Dist: mcp>=1.0.0
Requires-Dist: httpx>=0.27.0
Requires-Dist: pydantic>=2.0.0
Requires-Dist: pydantic-settings>=2.0.0
Requires-Dist: python-dotenv>=1.0.0
Provides-Extra: dev
Requires-Dist: pytest>=8.0.0; extra == "dev"
Requires-Dist: pytest-asyncio>=0.23.0; extra == "dev"
Requires-Dist: pytest-cov>=4.1.0; extra == "dev"
Requires-Dist: black>=24.0.0; extra == "dev"
Requires-Dist: ruff>=0.3.0; extra == "dev"
Requires-Dist: mypy>=1.8.0; extra == "dev"
Dynamic: license-file
